Workbook

Sheet Overview
A1: City General Fund: variance analysis, FY2019 to FY2023
A2: Source: Kaggle dataset "City Budget Summary and Recommendations", file fy2022-proposed-city-budget-book-1.csv (provided by the user). 1,533 rows, one fund (101: City General).
A4: Inputs (change the yellow cells; every flag in the workbook updates)
A5: Variance % threshold | B5: 0.1 | C5: A line is flagged REVIEW only when BOTH the % and $ thresholds are met (tiny accounts with big percentage swings are ignored).
A6: Variance $ threshold | B6: 250000 | C6: If the starting amount is zero, % is undefined, so the $ threshold alone decides.
A8: Fund totals ($)
A9: Metric | B9: FY2019 Actual | C9: FY2020 Actual | D9: FY2021 Budget | E9: FY2022 Recommend | F9: FY2023 Forecast
A10: Revenues (shown as positive) | B10: =-SUMIFS(Data!$H$2:$H$1534,Data!$C$2:$C$1534,"REVENUES") -> 498182808 | C10: =-SUMIFS(Data!$I$2:$I$1534,Data!$C$2:$C$1534,"REVENUES") -> 487205336 | D10: =-SUMIFS(Data!$J$2:$J$1534,Data!$C$2:$C$1534,"REVENUES") -> 510917760 | E10: =-SUMIFS(Data!$K$2:$K$1534,Data!$C$2:$C$1534,"REVENUES") -> 539937743 | F10: =-SUMIFS(Data!$L$2:$L$1534,Data!$C$2:$C$1534,"REVENUES") -> 543790104
A11: Expenses | B11: =SUMIFS(Data!$H$2:$H$1534,Data!$C$2:$C$1534,"EXPENSES") -> 489443567 | C11: =SUMIFS(Data!$I$2:$I$1534,Data!$C$2:$C$1534,"EXPENSES") -> 483004372 | D11: =SUMIFS(Data!$J$2:$J$1534,Data!$C$2:$C$1534,"EXPENSES") -> 510917760 | E11: =SUMIFS(Data!$K$2:$K$1534,Data!$C$2:$C$1534,"EXPENSES") -> 539937743 | F11: =SUMIFS(Data!$L$2:$L$1534,Data!$C$2:$C$1534,"EXPENSES") -> 556002789
A12: Net surplus / (deficit) | B12: =B10-B11 -> 8739241 | C12: =C10-C11 -> 4200964 | D12: =D10-D11 -> 0 | E12: =E10-E11 -> 0 | F12: =F10-F11 -> -12212685
A13: Expense growth vs prior column | B13: - | C13: =C11/B11-1 -> -0.013156154 | D13: =D11/C11-1 -> 0.05779117 | E13: =E11/D11-1 -> 0.056799715 | F13: =F11/E11-1 -> 0.029753515
A15: Flag counts (expense lines)
A16: Expense lines in file | B16: =COUNTIFS(Data!$C$2:$C$1534,"EXPENSES") -> 1339
A17: Flagged REVIEW: 2021 Budget vs 2020 Actual | B17: =COUNTIFS(Data!$C$2:$C$1534,"EXPENSES",Data!$O$2:$O$1534,"REVIEW*") -> 52
A18: Flagged REVIEW: 2022 Recommend vs 2021 Budget | B18: =COUNTIFS(Data!$C$2:$C$1534,"EXPENSES",Data!$R$2:$R$1534,"REVIEW*") -> 20
A20: How to use this workbook
A21: Division Summary and Department Summary roll the line-level data up with SUMIFS. Top Variances ranks the 15 biggest expense changes. Data holds the 1,533 source rows plus the variance formulas.
A22: In the yellow "Drivers and actions" cells, write why each flagged variance happened and what should happen next. Example format: "Salaries budget appears to absorb leave lines booked separately in 2020; confirm with budget office, then restate 2020 on the same basis."
A23: The charts on Division Summary update when the data or thresholds change.
A25: Limitations of this dataset (read before presenting)
A26: This is NOT a true same-year budget vs actual. The file has actuals for 2019 and 2020 and budget, recommended and forecast figures for 2021 to 2023, but no 2021 actuals. The variances here compare a budget with the last actual year (2021B vs 2020A) and a proposal with the current budget (2022R vs 2021B).
A27: Sign convention in the source: revenues are negative, expenses positive. All variance analysis here covers expenses only. A few expense lines hold small negative actuals (credits).
A28: Line-level changes can reflect account reclassification, not real spending changes. Treat flags as questions to investigate, not findings.
A29: The source file does not state the reason for any change. Anything written in the "Drivers and actions" column is your interpretation and should be confirmed with the budget owner.
A31: Colour legend
A32: Blue text | B32: Source data or an input you can change
A33: Black text | B33: Formula on the same sheet
A34: Green text | B34: Formula pulling from another sheet
A35: Red fill | B35: Flag = REVIEW

Sheet Division Summary
A1: Expense variance by division
A2: Expenses only, in dollars. Positive variance = higher spend. Flag = REVIEW when both the $ and % thresholds on the Overview sheet are met.
A4: Division | B4: 2019 Actual | C4: 2020 Actual | D4: 2021 Budget | E4: 2022 Recommend | F4: 2023 Forecast | G4: Var $ 2021B vs 2020A | H4: Var % 2021B vs 2020A | I4: Flag | J4: Var $ 2022R vs 2021B | K4: Var % 2022R vs 2021B | L4: Flag
A5: General (Non-Departmental) | B5: =SUMIFS(Data!$H$2:$H$1534,Data!$D$2:$D$1534,$A5,Data!$C$2:$C$1534,"EXPENSES") -> 233404683 | C5: =SUMIFS(Data!$I$2:$I$1534,Data!$D$2:$D$1534,$A5,Data!$C$2:$C$1534,"EXPENSES") -> 238870582 | D5: =SUMIFS(Data!$J$2:$J$1534,Data!$D$2:$D$1534,$A5,Data!$C$2:$C$1534,"EXPENSES") -> 229759583 | E5: =SUMIFS(Data!$K$2:$K$1534,Data!$D$2:$D$1534,$A5,Data!$C$2:$C$1534,"EXPENSES") -> 244148000 | F5: =SUMIFS(Data!$L$2:$L$1534,Data!$D$2:$D$1534,$A5,Data!$C$2:$C$1534,"EXPENSES") -> 253461670 | G5: =D5-C5 -> -9110999 | H5: =IF(C5=0,"n/a",G5/ABS(C5)) -> -0.038141989 | I5: =IF(ABS(G5)<Overview!$B$6,"OK",IF(C5=0,"REVIEW (zero base)",IF(ABS(G5/ABS(C5))>=Overview!$B$5,"REVIEW","OK"))) -> OK | J5: =E5-D5 -> 14388417 | K5: =IF(D5=0,"n/a",J5/ABS(D5)) -> 0.062623795 | L5: =IF(ABS(J5)<Overview!$B$6,"OK",IF(D5=0,"REVIEW (zero base)",IF(ABS(J5/ABS(D5))>=Overview!$B$5,"REVIEW","OK"))) -> OK
A6: Public Safety | B6: =SUMIFS(Data!$H$2:$H$1534,Data!$D$2:$D$1534,$A6,Data!$C$2:$C$1534,"EXPENSES") -> 163932338 | C6: =SUMIFS(Data!$I$2:$I$1534,Data!$D$2:$D$1534,$A6,Data!$C$2:$C$1534,"EXPENSES") -> 153389900 | D6: =SUMIFS(Data!$J$2:$J$1534,Data!$D$2:$D$1534,$A6,Data!$C$2:$C$1534,"EXPENSES") -> 184913932 | E6: =SUMIFS(Data!$K$2:$K$1534,Data!$D$2:$D$1534,$A6,Data!$C$2:$C$1534,"EXPENSES") -> 189616148 | F6: =SUMIFS(Data!$L$2:$L$1534,Data!$D$2:$D$1534,$A6,Data!$C$2:$C$1534,"EXPENSES") -> 195449323 | G6: =D6-C6 -> 31524032 | H6: =IF(C6=0,"n/a",G6/ABS(C6)) -> 0.2055157 | I6: =IF(ABS(G6)<Overview!$B$6,"OK",IF(C6=0,"REVIEW (zero base)",IF(ABS(G6/ABS(C6))>=Overview!$B$5,"REVIEW","OK"))) -> REVIEW | J6: =E6-D6 -> 4702216 | K6: =IF(D6=0,"n/a",J6/ABS(D6)) -> 0.025429214 | L6: =IF(ABS(J6)<Overview!$B$6,"OK",IF(D6=0,"REVIEW (zero base)",IF(ABS(J6/ABS(D6))>=Overview!$B$5,"REVIEW","OK"))) -> OK
A7: Department of Public Works | B7: =SUMIFS(Data!$H$2:$H$1534,Data!$D$2:$D$1534,$A7,Data!$C$2:$C$1534,"EXPENSES") -> 23136706 | C7: =SUMIFS(Data!$I$2:$I$1534,Data!$D$2:$D$1534,$A7,Data!$C$2:$C$1534,"EXPENSES") -> 22596031 | D7: =SUMIFS(Data!$J$2:$J$1534,Data!$D$2:$D$1534,$A7,Data!$C$2:$C$1534,"EXPENSES") -> 24725507 | E7: =SUMIFS(Data!$K$2:$K$1534,Data!$D$2:$D$1534,$A7,Data!$C$2:$C$1534,"EXPENSES") -> 26036349 | F7: =SUMIFS(Data!$L$2:$L$1534,Data!$D$2:$D$1534,$A7,Data!$C$2:$C$1534,"EXPENSES") -> 26319384 | G7: =D7-C7 -> 2129476 | H7: =IF(C7=0,"n/a",G7/ABS(C7)) -> 0.094241152 | I7: =IF(ABS(G7)<Overview!$B$6,"OK",IF(C7=0,"REVIEW (zero base)",IF(ABS(G7/ABS(C7))>=Overview!$B$5,"REVIEW","OK"))) -> OK | J7: =E7-D7 -> 1310842 | K7: =IF(D7=0,"n/a",J7/ABS(D7)) -> 0.053015778 | L7: =IF(ABS(J7)<Overview!$B$6,"OK",IF(D7=0,"REVIEW (zero base)",IF(ABS(J7/ABS(D7))>=Overview!$B$5,"REVIEW","OK"))) -> OK
A8: Parks | B8: =SUMIFS(Data!$H$2:$H$1534,Data!$D$2:$D$1534,$A8,Data!$C$2:$C$1534,"EXPENSES") -> 13229022 | C8: =SUMIFS(Data!$I$2:$I$1534,Data!$D$2:$D$1534,$A8,Data!$C$2:$C$1534,"EXPENSES") -> 13782764 | D8: =SUMIFS(Data!$J$2:$J$1534,Data!$D$2:$D$1534,$A8,Data!$C$2:$C$1534,"EXPENSES") -> 13902281 | E8: =SUMIFS(Data!$K$2:$K$1534,Data!$D$2:$D$1534,$A8,Data!$C$2:$C$1534,"EXPENSES") -> 15131122 | F8: =SUMIFS(Data!$L$2:$L$1534,Data!$D$2:$D$1534,$A8,Data!$C$2:$C$1534,"EXPENSES") -> 15387150 | G8: =D8-C8 -> 119517 | H8: =IF(C8=0,"n/a",G8/ABS(C8)) -> 0.0086714827 | I8: =IF(ABS(G8)<Overview!$B$6,"OK",IF(C8=0,"REVIEW (zero base)",IF(ABS(G8/ABS(C8))>=Overview!$B$5,"REVIEW","OK"))) -> OK | J8: =E8-D8 -> 1228841 | K8: =IF(D8=0,"n/a",J8/ABS(D8)) -> 0.088391322 | L8: =IF(ABS(J8)<Overview!$B$6,"OK",IF(D8=0,"REVIEW (zero base)",IF(ABS(J8/ABS(D8))>=Overview!$B$5,"REVIEW","OK"))) -> OK
A9: Public Property & Purchasing | B9: =SUMIFS(Data!$H$2:$H$1534,Data!$D$2:$D$1534,$A9,Data!$C$2:$C$1534,"EXPENSES") -> 8679036 | C9: =SUMIFS(Data!$I$2:$I$1534,Data!$D$2:$D$1534,$A9,Data!$C$2:$C$1534,"EXPENSES") -> 7502591 | D9: =SUMIFS(Data!$J$2:$J$1534,Data!$D$2:$D$1534,$A9,Data!$C$2:$C$1534,"EXPENSES") -> 7761845 | E9: =SUMIFS(Data!$K$2:$K$1534,Data!$D$2:$D$1534,$A9,Data!$C$2:$C$1534,"EXPENSES") -> 8046972 | F9: =SUMIFS(Data!$L$2:$L$1534,Data!$D$2:$D$1534,$A9,Data!$C$2:$C$1534,"EXPENSES") -> 8143094 | G9: =D9-C9 -> 259254 | H9: =IF(C9=0,"n/a",G9/ABS(C9)) -> 0.034555262 | I9: =IF(ABS(G9)<Overview!$B$6,"OK",IF(C9=0,"REVIEW (zero base)",IF(ABS(G9/ABS(C9))>=Overview!$B$5,"REVIEW","OK"))) -> OK | J9: =E9-D9 -> 285127 | K9: =IF(D9=0,"n/a",J9/ABS(D9)) -> 0.036734436 | L9: =IF(ABS(J9)<Overview!$B$6,"OK",IF(D9=0,"REVIEW (zero base)",IF(ABS(J9/ABS(D9))>=Overview!$B$5,"REVIEW","OK"))) -> OK
A10: Finance Departments | B10: =SUMIFS(Data!$H$2:$H$1534,Data!$D$2:$D$1534,$A10,Data!$C$2:$C$1534,"EXPENSES") -> 8081683 | C10: =SUMIFS(Data!$I$2:$I$1534,Data!$D$2:$D$1534,$A10,Data!$C$2:$C$1534,"EXPENSES") -> 7617151 | D10: =SUMIFS(Data!$J$2:$J$1534,Data!$D$2:$D$1534,$A10,Data!$C$2:$C$1534,"EXPENSES") -> 7446376 | E10: =SUMIFS(Data!$K$2:$K$1534,Data!$D$2:$D$1534,$A10,Data!$C$2:$C$1534,"EXPENSES") -> 8701561 | F10: =SUMIFS(Data!$L$2:$L$1534,Data!$D$2:$D$1534,$A10,Data!$C$2:$C$1534,"EXPENSES") -> 8312457 | G10: =D10-C10 -> -170775 | H10: =IF(C10=0,"n/a",G10/ABS(C10)) -> -0.0224198 | I10: =IF(ABS(G10)<Overview!$B$6,"OK",IF(C10=0,"REVIEW (zero base)",IF(ABS(G10/ABS(C10))>=Overview!$B$5,"REVIEW","OK"))) -> OK | J10: =E10-D10 -> 1255185 | K10: =IF(D10=0,"n/a",J10/ABS(D10)) -> 0.1685632 | L10: =IF(ABS(J10)<Overview!$B$6,"OK",IF(D10=0,"REVIEW (zero base)",IF(ABS(J10/ABS(D10))>=Overview!$B$5,"REVIEW","OK"))) -> REVIEW
A11: Law Department / City Solicitor | B11: =SUMIFS(Data!$H$2:$H$1534,Data!$D$2:$D$1534,$A11,Data!$C$2:$C$1534,"EXPENSES") -> 6930266 | C11: =SUMIFS(Data!$I$2:$I$1534,Data!$D$2:$D$1534,$A11,Data!$C$2:$C$1534,"EXPENSES") -> 6536800 | D11: =SUMIFS(Data!$J$2:$J$1534,Data!$D$2:$D$1534,$A11,Data!$C$2:$C$1534,"EXPENSES") -> 6046542 | E11: =SUMIFS(Data!$K$2:$K$1534,Data!$D$2:$D$1534,$A11,Data!$C$2:$C$1534,"EXPENSES") -> 6273172 | F11: =SUMIFS(Data!$L$2:$L$1534,Data!$D$2:$D$1534,$A11,Data!$C$2:$C$1534,"EXPENSES") -> 6361766 | G11: =D11-C11 -> -490258 | H11: =IF(C11=0,"n/a",G11/ABS(C11)) -> -0.074999694 | I11: =IF(ABS(G11)<Overview!$B$6,"OK",IF(C11=0,"REVIEW (zero base)",IF(ABS(G11/ABS(C11))>=Overview!$B$5,"REVIEW","OK"))) -> OK | J11: =E11-D11 -> 226630 | K11: =IF(D11=0,"n/a",J11/ABS(D11)) -> 0.037480927 | L11: =IF(ABS(J11)<Overview!$B$6,"OK",IF(D11=0,"REVIEW (zero base)",IF(ABS(J11/ABS(D11))>=Overview!$B$5,"REVIEW","OK"))) -> OK
A12: City Council | B12: =SUMIFS(Data!$H$2:$H$1534,Data!$D$2:$D$1534,$A12,Data!$C$2:$C$1534,"EXPENSES") -> 4464844 | C12: =SUMIFS(Data!$I$2:$I$1534,Data!$D$2:$D$1534,$A12,Data!$C$2:$C$1534,"EXPENSES") -> 4787969 | D12: =SUMIFS(Data!$J$2:$J$1534,Data!$D$2:$D$1534,$A12,Data!$C$2:$C$1534,"EXPENSES") -> 5731866 | E12: =SUMIFS(Data!$K$2:$K$1534,Data!$D$2:$D$1534,$A12,Data!$C$2:$C$1534,"EXPENSES") -> 6216840 | F12: =SUMIFS(Data!$L$2:$L$1534,Data!$D$2:$D$1534,$A12,Data!$C$2:$C$1534,"EXPENSES") -> 6300606 | G12: =D12-C12 -> 943897 | H12: =IF(C12=0,"n/a",G12/ABS(C12)) -> 0.19713933 | I12: =IF(ABS(G12)<Overview!$B$6,"OK",IF(C12=0,"REVIEW (zero base)",IF(ABS(G12/ABS(C12))>=Overview!$B$5,"REVIEW","OK"))) -> REVIEW | J12: =E12-D12 -> 484974 | K12: =IF(D12=0,"n/a",J12/ABS(D12)) -> 0.084610143 | L12: =IF(ABS(J12)<Overview!$B$6,"OK",IF(D12=0,"REVIEW (zero base)",IF(ABS(J12/ABS(D12))>=Overview!$B$5,"REVIEW","OK"))) -> OK
A13: Department of Inspections & Standards | B13: =SUMIFS(Data!$H$2:$H$1534,Data!$D$2:$D$1534,$A13,Data!$C$2:$C$1534,"EXPENSES") -> 3855019 | C13: =SUMIFS(Data!$I$2:$I$1534,Data!$D$2:$D$1534,$A13,Data!$C$2:$C$1534,"EXPENSES") -> 3863686 | D13: =SUMIFS(Data!$J$2:$J$1534,Data!$D$2:$D$1534,$A13,Data!$C$2:$C$1534,"EXPENSES") -> 4229312 | E13: =SUMIFS(Data!$K$2:$K$1534,Data!$D$2:$D$1534,$A13,Data!$C$2:$C$1534,"EXPENSES") -> 4514314 | F13: =SUMIFS(Data!$L$2:$L$1534,Data!$D$2:$D$1534,$A13,Data!$C$2:$C$1534,"EXPENSES") -> 4589619 | G13: =D13-C13 -> 365626 | H13: =IF(C13=0,"n/a",G13/ABS(C13)) -> 0.094631396 | I13: =IF(ABS(G13)<Overview!$B$6,"OK",IF(C13=0,"REVIEW (zero base)",IF(ABS(G13/ABS(C13))>=Overview!$B$5,"REVIEW","OK"))) -> OK | J13: =E13-D13 -> 285002 | K13: =IF(D13=0,"n/a",J13/ABS(D13)) -> 0.06738732 | L13: =IF(ABS(J13)<Overview!$B$6,"OK",IF(D13=0,"REVIEW (zero base)",IF(ABS(J13/ABS(D13))>=Overview!$B$5,"REVIEW","OK"))) -> OK
A14: Human Services | B14: =SUMIFS(Data!$H$2:$H$1534,Data!$D$2:$D$1534,$A14,Data!$C$2:$C$1534,"EXPENSES") -> 2145633 | C14: =SUMIFS(Data!$I$2:$I$1534,Data!$D$2:$D$1534,$A14,Data!$C$2:$C$1534,"EXPENSES") -> 2340410 | D14: =SUMIFS(Data!$J$2:$J$1534,Data!$D$2:$D$1534,$A14,Data!$C$2:$C$1534,"EXPENSES") -> 3804812 | E14: =SUMIFS(Data!$K$2:$K$1534,Data!$D$2:$D$1534,$A14,Data!$C$2:$C$1534,"EXPENSES") -> 4754322 | F14: =SUMIFS(Data!$L$2:$L$1534,Data!$D$2:$D$1534,$A14,Data!$C$2:$C$1534,"EXPENSES") -> 4795422 | G14: =D14-C14 -> 1464402 | H14: =IF(C14=0,"n/a",G14/ABS(C14)) -> 0.62570319 | I14: =IF(ABS(G14)<Overview!$B$6,"OK",IF(C14=0,"REVIEW (zero base)",IF(ABS(G14/ABS(C14))>=Overview!$B$5,"REVIEW","OK"))) -> REVIEW | J14: =E14-D14 -> 949510 | K14: =IF(D14=0,"n/a",J14/ABS(D14)) -> 0.24955504 | L14: =IF(ABS(J14)<Overview!$B$6,"OK",IF(D14=0,"REVIEW (zero base)",IF(ABS(J14/ABS(D14))>=Overview!$B$5,"REVIEW","OK"))) -> REVIEW
A15: Information Technology | B15: =SUMIFS(Data!$H$2:$H$1534,Data!$D$2:$D$1534,$A15,Data!$C$2:$C$1534,"EXPENSES") -> 3484604 | C15: =SUMIFS(Data!$I$2:$I$1534,Data!$D$2:$D$1534,$A15,Data!$C$2:$C$1534,"EXPENSES") -> 3488079 | D15: =SUMIFS(Data!$J$2:$J$1534,Data!$D$2:$D$1534,$A15,Data!$C$2:$C$1534,"EXPENSES") -> 3803524 | E15: =SUMIFS(Data!$K$2:$K$1534,Data!$D$2:$D$1534,$A15,Data!$C$2:$C$1534,"EXPENSES") -> 4299333 | F15: =SUMIFS(Data!$L$2:$L$1534,Data!$D$2:$D$1534,$A15,Data!$C$2:$C$1534,"EXPENSES") -> 4356660 | G15: =D15-C15 -> 315445 | H15: =IF(C15=0,"n/a",G15/ABS(C15)) -> 0.090435165 | I15: =IF(ABS(G15)<Overview!$B$6,"OK",IF(C15=0,"REVIEW (zero base)",IF(ABS(G15/ABS(C15))>=Overview!$B$5,"REVIEW","OK"))) -> OK | J15: =E15-D15 -> 495809 | K15: =IF(D15=0,"n/a",J15/ABS(D15)) -> 0.13035517 | L15: =IF(ABS(J15)<Overview!$B$6,"OK",IF(D15=0,"REVIEW (zero base)",IF(ABS(J15/ABS(D15))>=Overview!$B$5,"REVIEW","OK"))) -> REVIEW
A16: Planning & Urban Development | B16: =SUMIFS(Data!$H$2:$H$1534,Data!$D$2:$D$1534,$A16,Data!$C$2:$C$1534,"EXPENSES") -> 3553595 | C16: =SUMIFS(Data!$I$2:$I$1534,Data!$D$2:$D$1534,$A16,Data!$C$2:$C$1534,"EXPENSES") -> 3631272 | D16: =SUMIFS(Data!$J$2:$J$1534,Data!$D$2:$D$1534,$A16,Data!$C$2:$C$1534,"EXPENSES") -> 3507410 | E16: =SUMIFS(Data!$K$2:$K$1534,Data!$D$2:$D$1534,$A16,Data!$C$2:$C$1534,"EXPENSES") -> 3941012 | F16: =SUMIFS(Data!$L$2:$L$1534,Data!$D$2:$D$1534,$A16,Data!$C$2:$C$1534,"EXPENSES") -> 4007677 | G16: =D16-C16 -> -123862 | H16: =IF(C16=0,"n/a",G16/ABS(C16)) -> -0.034109811 | I16: =IF(ABS(G16)<Overview!$B$6,"OK",IF(C16=0,"REVIEW (zero base)",IF(ABS(G16/ABS(C16))>=Overview!$B$5,"REVIEW","OK"))) -> OK | J16: =E16-D16 -> 433602 | K16: =IF(D16=0,"n/a",J16/ABS(D16)) -> 0.12362455 | L16: =IF(ABS(J16)<Overview!$B$6,"OK",IF(D16=0,"REVIEW (zero base)",IF(ABS(J16/ABS(D16))>=Overview!$B$5,"REVIEW","OK"))) -> REVIEW
... A22: Office of Economic Opportunity | B22: =SUMIFS(Data!$H$2:$H$1534,Data!$D$2:$D$1534,$A22,Data!$C$2:$C$1534,"EXPENSES") -> 1779434 | C22: =SUMIFS(Data!$I$2:$I$1534,Data!$D$2:$D$1534,$A22,Data!$C$2:$C$1534,"EXPENSES") -> 1679079 | D22: =SUMIFS(Data!$J$2:$J$1534,Data!$D$2:$D$1534,$A22,Data!$C$2:$C$1534,"EXPENSES") -> 1800817 | E22: =SUMIFS(Data!$K$2:$K$1534,Data!$D$2:$D$1534,$A22,Data!$C$2:$C$1534,"EXPENSES") -> 1923935 | F22: =SUMIFS(Data!$L$2:$L$1534,Data!$D$2:$D$1534,$A22,Data!$C$2:$C$1534,"EXPENSES") -> 1942413 | G22: =D22-C22 -> 121738 | H22: =IF(C22=0,"n/a",G22/ABS(C22)) -> 0.072502842 | I22: =IF(ABS(G22)<Overview!$B$6,"OK",IF(C22=0,"REVIEW (zero base)",IF(ABS(G22/ABS(C22))>=Overview!$B$5,"REVIEW","OK"))) -> OK | J22: =E22-D22 -> 123118 | K22: =IF(D22=0,"n/a",J22/ABS(D22)) -> 0.068367857 | L22: =IF(ABS(J22)<Overview!$B$6,"OK",IF(D22=0,"REVIEW (zero base)",IF(ABS(J22/ABS(D22))>=Overview!$B$5,"REVIEW","OK"))) -> OK
A23: Total expenses | B23: =SUM(B5:B22) -> 489443567 | C23: =SUM(C5:C22) -> 483004372 | D23: =SUM(D5:D22) -> 510917760 | E23: =SUM(E5:E22) -> 539937743 | F23: =SUM(F5:F22) -> 556002789 | G23: =D23-C23 -> 27913388 | H23: =IF(C23=0,"n/a",G23/ABS(C23)) -> 0.05779117 | I23: =IF(ABS(G23)<Overview!$B$6,"OK",IF(C23=0,"REVIEW (zero base)",IF(ABS(G23/ABS(C23))>=Overview!$B$5,"REVIEW","OK"))) -> OK | J23: =E23-D23 -> 29019983 | K23: =IF(D23=0,"n/a",J23/ABS(D23)) -> 0.056799715 | L23: =IF(ABS(J23)<Overview!$B$6,"OK",IF(D23=0,"REVIEW (zero base)",IF(ABS(J23/ABS(D23))>=Overview!$B$5,"REVIEW","OK"))) -> OK
A24: Check vs Data (should be 0) | B24: =B23-SUMIFS(Data!$H$2:$H$1534,Data!$C$2:$C$1534,"EXPENSES") -> 0 | C24: =C23-SUMIFS(Data!$I$2:$I$1534,Data!$C$2:$C$1534,"EXPENSES") -> 0 | D24: =D23-SUMIFS(Data!$J$2:$J$1534,Data!$C$2:$C$1534,"EXPENSES") -> 0 | E24: =E23-SUMIFS(Data!$K$2:$K$1534,Data!$C$2:$C$1534,"EXPENSES") -> 0 | F24: =F23-SUMIFS(Data!$L$2:$L$1534,Data!$C$2:$C$1534,"EXPENSES") -> 0

Sheet Department Summary
A1: Expense variance by department
A2: Expenses only, in dollars. Positive variance = higher spend. Sorted by 2021 Budget (largest first).
A4: Department | B4: Division | C4: 2019 Actual | D4: 2020 Actual | E4: 2021 Budget | F4: 2022 Recommend | G4: 2023 Forecast | H4: Var $ 2021B vs 2020A | I4: Var % 2021B vs 2020A | J4: Flag | K4: Var $ 2022R vs 2021B | L4: Var % 2022R vs 2021B | M4: Flag
A5: 101-000: Non Departmental-General Fund | B5: General (Non-Departmental) | C5: =SUMIFS(Data!$H$2:$H$1534,Data!$E$2:$E$1534,$A5,Data!$C$2:$C$1534,"EXPENSES") -> 131141819 | D5: =SUMIFS(Data!$I$2:$I$1534,Data!$E$2:$E$1534,$A5,Data!$C$2:$C$1534,"EXPENSES") -> 134694954 | E5: =SUMIFS(Data!$J$2:$J$1534,Data!$E$2:$E$1534,$A5,Data!$C$2:$C$1534,"EXPENSES") -> 133214611 | F5: =SUMIFS(Data!$K$2:$K$1534,Data!$E$2:$E$1534,$A5,Data!$C$2:$C$1534,"EXPENSES") -> 137837350 | G5: =SUMIFS(Data!$L$2:$L$1534,Data!$E$2:$E$1534,$A5,Data!$C$2:$C$1534,"EXPENSES") -> 142796001 | H5: =E5-D5 -> -1480343 | I5: =IF(D5=0,"n/a",H5/ABS(D5)) -> -0.010990337 | J5: =IF(ABS(H5)<Overview!$B$6,"OK",IF(D5=0,"REVIEW (zero base)",IF(ABS(H5/ABS(D5))>=Overview!$B$5,"REVIEW","OK"))) -> OK | K5: =F5-E5 -> 4622739 | L5: =IF(E5=0,"n/a",K5/ABS(E5)) -> 0.034701441 | M5: =IF(ABS(K5)<Overview!$B$6,"OK",IF(E5=0,"REVIEW (zero base)",IF(ABS(K5/ABS(E5))>=Overview!$B$5,"REVIEW","OK"))) -> OK
A6: 101-302: Police | B6: Public Safety | C6: =SUMIFS(Data!$H$2:$H$1534,Data!$E$2:$E$1534,$A6,Data!$C$2:$C$1534,"EXPENSES") -> 84997596 | D6: =SUMIFS(Data!$I$2:$I$1534,Data!$E$2:$E$1534,$A6,Data!$C$2:$C$1534,"EXPENSES") -> 73467235 | E6: =SUMIFS(Data!$J$2:$J$1534,Data!$E$2:$E$1534,$A6,Data!$C$2:$C$1534,"EXPENSES") -> 91643503 | F6: =SUMIFS(Data!$K$2:$K$1534,Data!$E$2:$E$1534,$A6,Data!$C$2:$C$1534,"EXPENSES") -> 93816418 | G6: =SUMIFS(Data!$L$2:$L$1534,Data!$E$2:$E$1534,$A6,Data!$C$2:$C$1534,"EXPENSES") -> 97545249 | H6: =E6-D6 -> 18176268 | I6: =IF(D6=0,"n/a",H6/ABS(D6)) -> 0.24740645 | J6: =IF(ABS(H6)<Overview!$B$6,"OK",IF(D6=0,"REVIEW (zero base)",IF(ABS(H6/ABS(D6))>=Overview!$B$5,"REVIEW","OK"))) -> REVIEW | K6: =F6-E6 -> 2172915 | L6: =IF(E6=0,"n/a",K6/ABS(E6)) -> 0.023710519 | M6: =IF(ABS(K6)<Overview!$B$6,"OK",IF(E6=0,"REVIEW (zero base)",IF(ABS(K6/ABS(E6))>=Overview!$B$5,"REVIEW","OK"))) -> OK
A7: 101-303: Fire | B7: Public Safety | C7: =SUMIFS(Data!$H$2:$H$1534,Data!$E$2:$E$1534,$A7,Data!$C$2:$C$1534,"EXPENSES") -> 67100059 | D7: =SUMIFS(Data!$I$2:$I$1534,Data!$E$2:$E$1534,$A7,Data!$C$2:$C$1534,"EXPENSES") -> 68989373 | E7: =SUMIFS(Data!$J$2:$J$1534,Data!$E$2:$E$1534,$A7,Data!$C$2:$C$1534,"EXPENSES") -> 81319299 | F7: =SUMIFS(Data!$K$2:$K$1534,Data!$E$2:$E$1534,$A7,Data!$C$2:$C$1534,"EXPENSES") -> 82786691 | G7: =SUMIFS(Data!$L$2:$L$1534,Data!$E$2:$E$1534,$A7,Data!$C$2:$C$1534,"EXPENSES") -> 84715420 | H7: =E7-D7 -> 12329926 | I7: =IF(D7=0,"n/a",H7/ABS(D7)) -> 0.17872211 | J7: =IF(ABS(H7)<Overview!$B$6,"OK",IF(D7=0,"REVIEW (zero base)",IF(ABS(H7/ABS(D7))>=Overview!$B$5,"REVIEW","OK"))) -> REVIEW | K7: =F7-E7 -> 1467392 | L7: =IF(E7=0,"n/a",K7/ABS(E7)) -> 0.018044819 | M7: =IF(ABS(K7)<Overview!$B$6,"OK",IF(E7=0,"REVIEW (zero base)",IF(ABS(K7/ABS(E7))>=Overview!$B$5,"REVIEW","OK"))) -> OK
A8: 101-223: Debt Service | B8: General (Non-Departmental) | C8: =SUMIFS(Data!$H$2:$H$1534,Data!$E$2:$E$1534,$A8,Data!$C$2:$C$1534,"EXPENSES") -> 62913576 | D8: =SUMIFS(Data!$I$2:$I$1534,Data!$E$2:$E$1534,$A8,Data!$C$2:$C$1534,"EXPENSES") -> 60551056 | E8: =SUMIFS(Data!$J$2:$J$1534,Data!$E$2:$E$1534,$A8,Data!$C$2:$C$1534,"EXPENSES") -> 55344275 | F8: =SUMIFS(Data!$K$2:$K$1534,Data!$E$2:$E$1534,$A8,Data!$C$2:$C$1534,"EXPENSES") -> 65716345 | G8: =SUMIFS(Data!$L$2:$L$1534,Data!$E$2:$E$1534,$A8,Data!$C$2:$C$1534,"EXPENSES") -> 69505195 | H8: =E8-D8 -> -5206781 | I8: =IF(D8=0,"n/a",H8/ABS(D8)) -> -0.085989929 | J8: =IF(ABS(H8)<Overview!$B$6,"OK",IF(D8=0,"REVIEW (zero base)",IF(ABS(H8/ABS(D8))>=Overview!$B$5,"REVIEW","OK"))) -> OK | K8: =F8-E8 -> 10372070 | L8: =IF(E8=0,"n/a",K8/ABS(E8)) -> 0.18740999 | M8: =IF(ABS(K8)<Overview!$B$6,"OK",IF(E8=0,"REVIEW (zero base)",IF(ABS(K8/ABS(E8))>=Overview!$B$5,"REVIEW","OK"))) -> REVIEW
A9: 101-800: Benefits | B9: General (Non-Departmental) | C9: =SUMIFS(Data!$H$2:$H$1534,Data!$E$2:$E$1534,$A9,Data!$C$2:$C$1534,"EXPENSES") -> 26506719 | D9: =SUMIFS(Data!$I$2:$I$1534,Data!$E$2:$E$1534,$A9,Data!$C$2:$C$1534,"EXPENSES") -> 29662504 | E9: =SUMIFS(Data!$J$2:$J$1534,Data!$E$2:$E$1534,$A9,Data!$C$2:$C$1534,"EXPENSES") -> 28127393 | F9: =SUMIFS(Data!$K$2:$K$1534,Data!$E$2:$E$1534,$A9,Data!$C$2:$C$1534,"EXPENSES") -> 27562182 | G9: =SUMIFS(Data!$L$2:$L$1534,Data!$E$2:$E$1534,$A9,Data!$C$2:$C$1534,"EXPENSES") -> 28126426 | H9: =E9-D9 -> -1535111 | I9: =IF(D9=0,"n/a",H9/ABS(D9)) -> -0.051752576 | J9: =IF(ABS(H9)<Overview!$B$6,"OK",IF(D9=0,"REVIEW (zero base)",IF(ABS(H9/ABS(D9))>=Overview!$B$5,"REVIEW","OK"))) -> OK | K9: =F9-E9 -> -565211 | L9: =IF(E9=0,"n/a",K9/ABS(E9)) -> -0.020094681 | M9: =IF(ABS(K9)<Overview!$B$6,"OK",IF(E9=0,"REVIEW (zero base)",IF(ABS(K9/ABS(E9))>=Overview!$B$5,"REVIEW","OK"))) -> OK
A10: 101-506: Environmental Control | B10: Department of Public Works | C10: =SUMIFS(Data!$H$2:$H$1534,Data!$E$2:$E$1534,$A10,Data!$C$2:$C$1534,"EXPENSES") -> 10892826 | D10: =SUMIFS(Data!$I$2:$I$1534,Data!$E$2:$E$1534,$A10,Data!$C$2:$C$1534,"EXPENSES") -> 11648669 | E10: =SUMIFS(Data!$J$2:$J$1534,Data!$E$2:$E$1534,$A10,Data!$C$2:$C$1534,"EXPENSES") -> 11762322 | F10: =SUMIFS(Data!$K$2:$K$1534,Data!$E$2:$E$1534,$A10,Data!$C$2:$C$1534,"EXPENSES") -> 12243292 | G10: =SUMIFS(Data!$L$2:$L$1534,Data!$E$2:$E$1534,$A10,Data!$C$2:$C$1534,"EXPENSES") -> 12339411 | H10: =E10-D10 -> 113653 | I10: =IF(D10=0,"n/a",H10/ABS(D10)) -> 0.009756737 | J10: =IF(ABS(H10)<Overview!$B$6,"OK",IF(D10=0,"REVIEW (zero base)",IF(ABS(H10/ABS(D10))>=Overview!$B$5,"REVIEW","OK"))) -> OK | K10: =F10-E10 -> 480970 | L10: =IF(E10=0,"n/a",K10/ABS(E10)) -> 0.040890736 | M10: =IF(ABS(K10)<Overview!$B$6,"OK",IF(E10=0,"REVIEW (zero base)",IF(ABS(K10/ABS(E10))>=Overview!$B$5,"REVIEW","OK"))) -> OK
A11: 101-304: Communications | B11: Public Safety | C11: =SUMIFS(Data!$H$2:$H$1534,Data!$E$2:$E$1534,$A11,Data!$C$2:$C$1534,"EXPENSES") -> 9432190 | D11: =SUMIFS(Data!$I$2:$I$1534,Data!$E$2:$E$1534,$A11,Data!$C$2:$C$1534,"EXPENSES") -> 8899968 | E11: =SUMIFS(Data!$J$2:$J$1534,Data!$E$2:$E$1534,$A11,Data!$C$2:$C$1534,"EXPENSES") -> 9213734 | F11: =SUMIFS(Data!$K$2:$K$1534,Data!$E$2:$E$1534,$A11,Data!$C$2:$C$1534,"EXPENSES") -> 10090963 | G11: =SUMIFS(Data!$L$2:$L$1534,Data!$E$2:$E$1534,$A11,Data!$C$2:$C$1534,"EXPENSES") -> 10226536 | H11: =E11-D11 -> 313766 | I11: =IF(D11=0,"n/a",H11/ABS(D11)) -> 0.035254734 | J11: =IF(ABS(H11)<Overview!$B$6,"OK",IF(D11=0,"REVIEW (zero base)",IF(ABS(H11/ABS(D11))>=Overview!$B$5,"REVIEW","OK"))) -> OK | K11: =F11-E11 -> 877229 | L11: =IF(E11=0,"n/a",K11/ABS(E11)) -> 0.095208848 | M11: =IF(ABS(K11)<Overview!$B$6,"OK",IF(E11=0,"REVIEW (zero base)",IF(ABS(K11/ABS(E11))>=Overview!$B$5,"REVIEW","OK"))) -> OK
A12: 101-1801: Public Property | B12: Public Property & Purchasing | C12: =SUMIFS(Data!$H$2:$H$1534,Data!$E$2:$E$1534,$A12,Data!$C$2:$C$1534,"EXPENSES") -> 8679036 | D12: =SUMIFS(Data!$I$2:$I$1534,Data!$E$2:$E$1534,$A12,Data!$C$2:$C$1534,"EXPENSES") -> 7502847 | E12: =SUMIFS(Data!$J$2:$J$1534,Data!$E$2:$E$1534,$A12,Data!$C$2:$C$1534,"EXPENSES") -> 7761845 | F12: =SUMIFS(Data!$K$2:$K$1534,Data!$E$2:$E$1534,$A12,Data!$C$2:$C$1534,"EXPENSES") -> 8046972 | G12: =SUMIFS(Data!$L$2:$L$1534,Data!$E$2:$E$1534,$A12,Data!$C$2:$C$1534,"EXPENSES") -> 8143094 | H12: =E12-D12 -> 258998 | I12: =IF(D12=0,"n/a",H12/ABS(D12)) -> 0.034519963 | J12: =IF(ABS(H12)<Overview!$B$6,"OK",IF(D12=0,"REVIEW (zero base)",IF(ABS(H12/ABS(D12))>=Overview!$B$5,"REVIEW","OK"))) -> OK | K12: =F12-E12 -> 285127 | L12: =IF(E12=0,"n/a",K12/ABS(E12)) -> 0.036734436 | M12: =IF(ABS(K12)<Overview!$B$6,"OK",IF(E12=0,"REVIEW (zero base)",IF(ABS(K12/ABS(E12))>=Overview!$B$5,"REVIEW","OK"))) -> OK
A13: 101-1400: Grants Commissions & Misc. | B13: General (Non-Departmental) | C13: =SUMIFS(Data!$H$2:$H$1534,Data!$E$2:$E$1534,$A13,Data!$C$2:$C$1534,"EXPENSES") -> 5621162 | D13: =SUMIFS(Data!$I$2:$I$1534,Data!$E$2:$E$1534,$A13,Data!$C$2:$C$1534,"EXPENSES") -> 5902662 | E13: =SUMIFS(Data!$J$2:$J$1534,Data!$E$2:$E$1534,$A13,Data!$C$2:$C$1534,"EXPENSES") -> 6304750 | F13: =SUMIFS(Data!$K$2:$K$1534,Data!$E$2:$E$1534,$A13,Data!$C$2:$C$1534,"EXPENSES") -> 6354750 | G13: =SUMIFS(Data!$L$2:$L$1534,Data!$E$2:$E$1534,$A13,Data!$C$2:$C$1534,"EXPENSES") -> 6354750 | H13: =E13-D13 -> 402088 | I13: =IF(D13=0,"n/a",H13/ABS(D13)) -> 0.068119774 | J13: =IF(ABS(H13)<Overview!$B$6,"OK",IF(D13=0,"REVIEW (zero base)",IF(ABS(H13/ABS(D13))>=Overview!$B$5,"REVIEW","OK"))) -> OK | K13: =F13-E13 -> 50000 | L13: =IF(E13=0,"n/a",K13/ABS(E13)) -> 0.0079305286 | M13: =IF(ABS(K13)<Overview!$B$6,"OK",IF(E13=0,"REVIEW (zero base)",IF(ABS(K13/ABS(E13))>=Overview!$B$5,"REVIEW","OK"))) -> OK
A14: 101-105: Law Department | B14: Law Department / City Solicitor | C14: =SUMIFS(Data!$H$2:$H$1534,Data!$E$2:$E$1534,$A14,Data!$C$2:$C$1534,"EXPENSES") -> 6930266 | D14: =SUMIFS(Data!$I$2:$I$1534,Data!$E$2:$E$1534,$A14,Data!$C$2:$C$1534,"EXPENSES") -> 6536800 | E14: =SUMIFS(Data!$J$2:$J$1534,Data!$E$2:$E$1534,$A14,Data!$C$2:$C$1534,"EXPENSES") -> 6046542 | F14: =SUMIFS(Data!$K$2:$K$1534,Data!$E$2:$E$1534,$A14,Data!$C$2:$C$1534,"EXPENSES") -> 6273172 | G14: =SUMIFS(Data!$L$2:$L$1534,Data!$E$2:$E$1534,$A14,Data!$C$2:$C$1534,"EXPENSES") -> 6361766 | H14: =E14-D14 -> -490258 | I14: =IF(D14=0,"n/a",H14/ABS(D14)) -> -0.074999694 | J14: =IF(ABS(H14)<Overview!$B$6,"OK",IF(D14=0,"REVIEW (zero base)",IF(ABS(H14/ABS(D14))>=Overview!$B$5,"REVIEW","OK"))) -> OK | K14: =F14-E14 -> 226630 | L14: =IF(E14=0,"n/a",K14/ABS(E14)) -> 0.037480927 | M14: =IF(ABS(K14)<Overview!$B$6,"OK",IF(E14=0,"REVIEW (zero base)",IF(ABS(K14/ABS(E14))>=Overview!$B$5,"REVIEW","OK"))) -> OK
A15: 101-702: Neighborhood Park Services | B15: Parks | C15: =SUMIFS(Data!$H$2:$H$1534,Data!$E$2:$E$1534,$A15,Data!$C$2:$C$1534,"EXPENSES") -> 5349123 | D15: =SUMIFS(Data!$I$2:$I$1534,Data!$E$2:$E$1534,$A15,Data!$C$2:$C$1534,"EXPENSES") -> 5622696 | E15: =SUMIFS(Data!$J$2:$J$1534,Data!$E$2:$E$1534,$A15,Data!$C$2:$C$1534,"EXPENSES") -> 5553951 | F15: =SUMIFS(Data!$K$2:$K$1534,Data!$E$2:$E$1534,$A15,Data!$C$2:$C$1534,"EXPENSES") -> 6631036 | G15: =SUMIFS(Data!$L$2:$L$1534,Data!$E$2:$E$1534,$A15,Data!$C$2:$C$1534,"EXPENSES") -> 6733805 | H15: =E15-D15 -> -68745 | I15: =IF(D15=0,"n/a",H15/ABS(D15)) -> -0.012226341 | J15: =IF(ABS(H15)<Overview!$B$6,"OK",IF(D15=0,"REVIEW (zero base)",IF(ABS(H15/ABS(D15))>=Overview!$B$5,"REVIEW","OK"))) -> OK | K15: =F15-E15 -> 1077085 | L15: =IF(E15=0,"n/a",K15/ABS(E15)) -> 0.19393131 | M15: =IF(ABS(K15)<Overview!$B$6,"OK",IF(E15=0,"REVIEW (zero base)",IF(ABS(K15/ABS(E15))>=Overview!$B$5,"REVIEW","OK"))) -> REVIEW
A16: 101-01803: Heat Power & Light | B16: General (Non-Departmental) | C16: =SUMIFS(Data!$H$2:$H$1534,Data!$E$2:$E$1534,$A16,Data!$C$2:$C$1534,"EXPENSES") -> 5075227 | D16: =SUMIFS(Data!$I$2:$I$1534,Data!$E$2:$E$1534,$A16,Data!$C$2:$C$1534,"EXPENSES") -> 6032397 | E16: =SUMIFS(Data!$J$2:$J$1534,Data!$E$2:$E$1534,$A16,Data!$C$2:$C$1534,"EXPENSES") -> 4642960 | F16: =SUMIFS(Data!$K$2:$K$1534,Data!$E$2:$E$1534,$A16,Data!$C$2:$C$1534,"EXPENSES") -> 4578247 | G16: =SUMIFS(Data!$L$2:$L$1534,Data!$E$2:$E$1534,$A16,Data!$C$2:$C$1534,"EXPENSES") -> 4578247 | H16: =E16-D16 -> -1389437 | I16: =IF(D16=0,"n/a",H16/ABS(D16)) -> -0.23032917 | J16: =IF(ABS(H16)<Overview!$B$6,"OK",IF(D16=0,"REVIEW (zero base)",IF(ABS(H16/ABS(D16))>=Overview!$B$5,"REVIEW","OK"))) -> REVIEW | K16: =F16-E16 -> -64713 | L16: =IF(E16=0,"n/a",K16/ABS(E16)) -> -0.013937876 | M16: =IF(ABS(K16)<Overview!$B$6,"OK",IF(E16=0,"REVIEW (zero base)",IF(ABS(K16/ABS(E16))>=Overview!$B$5,"REVIEW","OK"))) -> OK
... A76: 101-918: Parking Administration | B76: Human Services | C76: =SUMIFS(Data!$H$2:$H$1534,Data!$E$2:$E$1534,$A76,Data!$C$2:$C$1534,"EXPENSES") -> 10568 | D76: =SUMIFS(Data!$I$2:$I$1534,Data!$E$2:$E$1534,$A76,Data!$C$2:$C$1534,"EXPENSES") -> 0 | E76: =SUMIFS(Data!$J$2:$J$1534,Data!$E$2:$E$1534,$A76,Data!$C$2:$C$1534,"EXPENSES") -> 0 | F76: =SUMIFS(Data!$K$2:$K$1534,Data!$E$2:$E$1534,$A76,Data!$C$2:$C$1534,"EXPENSES") -> 0 | G76: =SUMIFS(Data!$L$2:$L$1534,Data!$E$2:$E$1534,$A76,Data!$C$2:$C$1534,"EXPENSES") -> 0 | H76: =E76-D76 -> 0 | I76: =IF(D76=0,"n/a",H76/ABS(D76)) -> n/a | J76: =IF(ABS(H76)<Overview!$B$6,"OK",IF(D76=0,"REVIEW (zero base)",IF(ABS(H76/ABS(D76))>=Overview!$B$5,"REVIEW","OK"))) -> OK | K76: =F76-E76 -> 0 | L76: =IF(E76=0,"n/a",K76/ABS(E76)) -> n/a | M76: =IF(ABS(K76)<Overview!$B$6,"OK",IF(E76=0,"REVIEW (zero base)",IF(ABS(K76/ABS(E76))>=Overview!$B$5,"REVIEW","OK"))) -> OK
A77: Total expenses | C77: =SUM(C5:C76) -> 489443567 | D77: =SUM(D5:D76) -> 483004372 | E77: =SUM(E5:E76) -> 510917760 | F77: =SUM(F5:F76) -> 539937743 | G77: =SUM(G5:G76) -> 556002789 | H77: =E77-D77 -> 27913388 | I77: =IF(D77=0,"n/a",H77/ABS(D77)) -> 0.05779117 | J77: =IF(ABS(H77)<Overview!$B$6,"OK",IF(D77=0,"REVIEW (zero base)",IF(ABS(H77/ABS(D77))>=Overview!$B$5,"REVIEW","OK"))) -> OK | K77: =F77-E77 -> 29019983 | L77: =IF(E77=0,"n/a",K77/ABS(E77)) -> 0.056799715 | M77: =IF(ABS(K77)<Overview!$B$6,"OK",IF(E77=0,"REVIEW (zero base)",IF(ABS(K77/ABS(E77))>=Overview!$B$5,"REVIEW","OK"))) -> OK
A78: Check vs Data (should be 0) | C78: =C77-SUMIFS(Data!$H$2:$H$1534,Data!$C$2:$C$1534,"EXPENSES") -> 0 | D78: =D77-SUMIFS(Data!$I$2:$I$1534,Data!$C$2:$C$1534,"EXPENSES") -> 0 | E78: =E77-SUMIFS(Data!$J$2:$J$1534,Data!$C$2:$C$1534,"EXPENSES") -> 0 | F78: =F77-SUMIFS(Data!$K$2:$K$1534,Data!$C$2:$C$1534,"EXPENSES") -> 0 | G78: =G77-SUMIFS(Data!$L$2:$L$1534,Data!$C$2:$C$1534,"EXPENSES") -> 0

Sheet Top Variances
A1: Top 15 expense lines by size of budgeted change
A2: Ranked by absolute $ change, 2021 Budget vs 2020 Actual. Ranking updates from the Data sheet.
A4: Rank | B4: Data row | C4: Division | D4: Department | E4: GL Account | F4: 2020 Actual | G4: 2021 Budget | H4: 2022 Recommend | I4: Var $ 2021B vs 2020A | J4: Var % 2021B vs 2020A | K4: Flag
A5: 1 | B5: =MATCH(LARGE(Data!$S$2:$S$1534,A5),Data!$S$2:$S$1534,0) -> 1100 | C5: =INDEX(Data!$D$2:$D$1534,$B5) -> Public Safety | D5: =INDEX(Data!$E$2:$E$1534,$B5) -> 101-302: Police | E5: =INDEX(Data!$G$2:$G$1534,$B5) -> SALARIES | F5: =INDEX(Data!$I$2:$I$1534,$B5) -> 18995717 | G5: =INDEX(Data!$J$2:$J$1534,$B5) -> 36519784 | H5: =INDEX(Data!$K$2:$K$1534,$B5) -> 38765000 | I5: =INDEX(Data!$M$2:$M$1534,$B5) -> 17524067 | J5: =INDEX(Data!$N$2:$N$1534,$B5) -> 0.92252727 | K5: =INDEX(Data!$O$2:$O$1534,$B5) -> REVIEW
A6: 2 | B6: =MATCH(LARGE(Data!$S$2:$S$1534,A6),Data!$S$2:$S$1534,0) -> 1172 | C6: =INDEX(Data!$D$2:$D$1534,$B6) -> Public Safety | D6: =INDEX(Data!$E$2:$E$1534,$B6) -> 101-303: Fire | E6: =INDEX(Data!$G$2:$G$1534,$B6) -> SALARIES | F6: =INDEX(Data!$I$2:$I$1534,$B6) -> 17713441 | G6: =INDEX(Data!$J$2:$J$1534,$B6) -> 31499640 | H6: =INDEX(Data!$K$2:$K$1534,$B6) -> 31398720 | I6: =INDEX(Data!$M$2:$M$1534,$B6) -> 13786199 | J6: =INDEX(Data!$N$2:$N$1534,$B6) -> 0.77829028 | K6: =INDEX(Data!$O$2:$O$1534,$B6) -> REVIEW
A7: 3 | B7: =MATCH(LARGE(Data!$S$2:$S$1534,A7),Data!$S$2:$S$1534,0) -> 220 | C7: =INDEX(Data!$D$2:$D$1534,$B7) -> General (Non-Departmental) | D7: =INDEX(Data!$E$2:$E$1534,$B7) -> 101-223: Debt Service | E7: =INDEX(Data!$G$2:$G$1534,$B7) -> INTEREST RENTAL PAYMENTS - PPBA | F7: =INDEX(Data!$I$2:$I$1534,$B7) -> 21223227 | G7: =INDEX(Data!$J$2:$J$1534,$B7) -> 8047154 | H7: =INDEX(Data!$K$2:$K$1534,$B7) -> 16010029 | I7: =INDEX(Data!$M$2:$M$1534,$B7) -> -13176073 | J7: =INDEX(Data!$N$2:$N$1534,$B7) -> -0.62083268 | K7: =INDEX(Data!$O$2:$O$1534,$B7) -> REVIEW
A8: 4 | B8: =MATCH(LARGE(Data!$S$2:$S$1534,A8),Data!$S$2:$S$1534,0) -> 219 | C8: =INDEX(Data!$D$2:$D$1534,$B8) -> General (Non-Departmental) | D8: =INDEX(Data!$E$2:$E$1534,$B8) -> 101-223: Debt Service | E8: =INDEX(Data!$G$2:$G$1534,$B8) -> PRINCIPAL RENTAL PAYMENTS - PPBA | F8: =INDEX(Data!$I$2:$I$1534,$B8) -> 5432171 | G8: =INDEX(Data!$J$2:$J$1534,$B8) -> 10410001 | H8: =INDEX(Data!$K$2:$K$1534,$B8) -> 29864167 | I8: =INDEX(Data!$M$2:$M$1534,$B8) -> 4977830 | J8: =INDEX(Data!$N$2:$N$1534,$B8) -> 0.91636106 | K8: =INDEX(Data!$O$2:$O$1534,$B8) -> REVIEW
A9: 5 | B9: =MATCH(LARGE(Data!$S$2:$S$1534,A9),Data!$S$2:$S$1534,0) -> 213 | C9: =INDEX(Data!$D$2:$D$1534,$B9) -> General (Non-Departmental) | D9: =INDEX(Data!$E$2:$E$1534,$B9) -> 101-223: Debt Service | E9: =INDEX(Data!$G$2:$G$1534,$B9) -> DEBT SERVICE - PRINCIPAL | F9: =INDEX(Data!$I$2:$I$1534,$B9) -> 17584223 | G9: =INDEX(Data!$J$2:$J$1534,$B9) -> 21855410 | H9: =INDEX(Data!$K$2:$K$1534,$B9) -> 9446223 | I9: =INDEX(Data!$M$2:$M$1534,$B9) -> 4271187 | J9: =INDEX(Data!$N$2:$N$1534,$B9) -> 0.24289882 | K9: =INDEX(Data!$O$2:$O$1534,$B9) -> REVIEW
A10: 6 | B10: =MATCH(LARGE(Data!$S$2:$S$1534,A10),Data!$S$2:$S$1534,0) -> 1119 | C10: =INDEX(Data!$D$2:$D$1534,$B10) -> Public Safety | D10: =INDEX(Data!$E$2:$E$1534,$B10) -> 101-302: Police | E10: =INDEX(Data!$G$2:$G$1534,$B10) -> CITY OF PROVIDENCE PENSION EXPENSE | F10: =INDEX(Data!$I$2:$I$1534,$B10) -> 27693212 | G10: =INDEX(Data!$J$2:$J$1534,$B10) -> 30690292 | H10: =INDEX(Data!$K$2:$K$1534,$B10) -> 32397111 | I10: =INDEX(Data!$M$2:$M$1534,$B10) -> 2997080 | J10: =INDEX(Data!$N$2:$N$1534,$B10) -> 0.10822435 | K10: =INDEX(Data!$O$2:$O$1534,$B10) -> REVIEW
A11: 7 | B11: =MATCH(LARGE(Data!$S$2:$S$1534,A11),Data!$S$2:$S$1534,0) -> 1108 | C11: =INDEX(Data!$D$2:$D$1534,$B11) -> Public Safety | D11: =INDEX(Data!$E$2:$E$1534,$B11) -> 101-302: Police | E11: =INDEX(Data!$G$2:$G$1534,$B11) -> CALL BACK | F11: =INDEX(Data!$I$2:$I$1534,$B11) -> 1291331 | G11: =INDEX(Data!$J$2:$J$1534,$B11) -> 3500000 | H11: =INDEX(Data!$K$2:$K$1534,$B11) -> 1450000 | I11: =INDEX(Data!$M$2:$M$1534,$B11) -> 2208669 | J11: =INDEX(Data!$N$2:$N$1534,$B11) -> 1.7103818 | K11: =INDEX(Data!$O$2:$O$1534,$B11) -> REVIEW
A12: 8 | B12: =MATCH(LARGE(Data!$S$2:$S$1534,A12),Data!$S$2:$S$1534,0) -> 1106 | C12: =INDEX(Data!$D$2:$D$1534,$B12) -> Public Safety | D12: =INDEX(Data!$E$2:$E$1534,$B12) -> 101-302: Police | E12: =INDEX(Data!$G$2:$G$1534,$B12) -> VACATION | F12: =INDEX(Data!$I$2:$I$1534,$B12) -> 2183873 | G12: =INDEX(Data!$J$2:$J$1534,$B12) -> 0 | H12: =INDEX(Data!$K$2:$K$1534,$B12) -> 0 | I12: =INDEX(Data!$M$2:$M$1534,$B12) -> -2183873 | J12: =INDEX(Data!$N$2:$N$1534,$B12) -> -1 | K12: =INDEX(Data!$O$2:$O$1534,$B12) -> REVIEW
A13: 9 | B13: =MATCH(LARGE(Data!$S$2:$S$1534,A13),Data!$S$2:$S$1534,0) -> 1176 | C13: =INDEX(Data!$D$2:$D$1534,$B13) -> Public Safety | D13: =INDEX(Data!$E$2:$E$1534,$B13) -> 101-303: Fire | E13: =INDEX(Data!$G$2:$G$1534,$B13) -> VACATION | F13: =INDEX(Data!$I$2:$I$1534,$B13) -> 1798963 | G13: =INDEX(Data!$J$2:$J$1534,$B13) -> 0 | H13: =INDEX(Data!$K$2:$K$1534,$B13) -> 0 | I13: =INDEX(Data!$M$2:$M$1534,$B13) -> -1798963 | J13: =INDEX(Data!$N$2:$N$1534,$B13) -> -1 | K13: =INDEX(Data!$O$2:$O$1534,$B13) -> REVIEW
A14: 10 | B14: =MATCH(LARGE(Data!$S$2:$S$1534,A14),Data!$S$2:$S$1534,0) -> 1178 | C14: =INDEX(Data!$D$2:$D$1534,$B14) -> Public Safety | D14: =INDEX(Data!$E$2:$E$1534,$B14) -> 101-303: Fire | E14: =INDEX(Data!$G$2:$G$1534,$B14) -> CALL BACK | F14: =INDEX(Data!$I$2:$I$1534,$B14) -> 3815598 | G14: =INDEX(Data!$J$2:$J$1534,$B14) -> 5400000 | H14: =INDEX(Data!$K$2:$K$1534,$B14) -> 5400000 | I14: =INDEX(Data!$M$2:$M$1534,$B14) -> 1584402 | J14: =INDEX(Data!$N$2:$N$1534,$B14) -> 0.41524343 | K14: =INDEX(Data!$O$2:$O$1534,$B14) -> REVIEW
A15: 11 | B15: =MATCH(LARGE(Data!$S$2:$S$1534,A15),Data!$S$2:$S$1534,0) -> 1222 | C15: =INDEX(Data!$D$2:$D$1534,$B15) -> Public Safety | D15: =INDEX(Data!$E$2:$E$1534,$B15) -> 101-304: Communications | E15: =INDEX(Data!$G$2:$G$1534,$B15) -> SALARIES | F15: =INDEX(Data!$I$2:$I$1534,$B15) -> 2509881 | G15: =INDEX(Data!$J$2:$J$1534,$B15) -> 3996901 | H15: =INDEX(Data!$K$2:$K$1534,$B15) -> 4324684 | I15: =INDEX(Data!$M$2:$M$1534,$B15) -> 1487020 | J15: =INDEX(Data!$N$2:$N$1534,$B15) -> 0.59246634 | K15: =INDEX(Data!$O$2:$O$1534,$B15) -> REVIEW
A16: 12 | B16: =MATCH(LARGE(Data!$S$2:$S$1534,A16),Data!$S$2:$S$1534,0) -> 1104 | C16: =INDEX(Data!$D$2:$D$1534,$B16) -> Public Safety | D16: =INDEX(Data!$E$2:$E$1534,$B16) -> 101-302: Police | E16: =INDEX(Data!$G$2:$G$1534,$B16) -> SICK LEAVE | F16: =INDEX(Data!$I$2:$I$1534,$B16) -> 1415261 | G16: =INDEX(Data!$J$2:$J$1534,$B16) -> 0 | H16: =INDEX(Data!$K$2:$K$1534,$B16) -> 0 | I16: =INDEX(Data!$M$2:$M$1534,$B16) -> -1415261 | J16: =INDEX(Data!$N$2:$N$1534,$B16) -> -1 | K16: =INDEX(Data!$O$2:$O$1534,$B16) -> REVIEW
... A19: 15 | B19: =MATCH(LARGE(Data!$S$2:$S$1534,A19),Data!$S$2:$S$1534,0) -> 235 | C19: =INDEX(Data!$D$2:$D$1534,$B19) -> General (Non-Departmental) | D19: =INDEX(Data!$E$2:$E$1534,$B19) -> 101-800: Benefits | E19: =INDEX(Data!$G$2:$G$1534,$B19) -> TRANSFER TO RETIREE MEDICAL INS FUND | F19: =INDEX(Data!$I$2:$I$1534,$B19) -> 29134481 | G19: =INDEX(Data!$J$2:$J$1534,$B19) -> 27757393 | H19: =INDEX(Data!$K$2:$K$1534,$B19) -> 27212182 | I19: =INDEX(Data!$M$2:$M$1534,$B19) -> -1377088 | J19: =INDEX(Data!$N$2:$N$1534,$B19) -> -0.047266605 | K19: =INDEX(Data!$O$2:$O$1534,$B19) -> OK
A21: Data row = position within the Data sheet range (row 1 of the range is the first data row).

Sheet Data
A1: Row ID | B1: Fund | C1: Account Type | D1: Division | E1: Department | F1: Summary Account | G1: GL Account | H1: 2019 Actual ($) | I1: 2020 Actual ($) | J1: 2021 Budget ($) | K1: 2022 Recommend ($) | L1: 2023 Forecast ($) | M1: Var $: 2021B vs 2020A | N1: Var %: 2021B vs 2020A | O1: Flag: 2021B vs 2020A | P1: Var $: 2022R vs 2021B | Q1: Var %: 2022R vs 2021B | R1: Flag: 2022R vs 2021B | S1: Rank key (expenses)
A2: 0 | B2: 101: City General | C2: REVENUES | D2: General (Non-Departmental) | E2: 101-000: Non Departmental-General Fund | F2: 41000: Total TAX REVENUES | G2: PROPERTY TAX REVENUE | H2: -275045271 | I2: -280548133 | J2: -274542432 | K2: -281901992 | L2: -287440350 | M2: =J2-I2 -> 6005701 | N2: =IF(I2=0,"n/a",M2/ABS(I2)) -> 0.021407025 | O2: =IF(ABS(M2)<Overview!$B$6,"OK",IF(I2=0,"REVIEW (zero base)",IF(ABS(M2/ABS(I2))>=Overview!$B$5,"REVIEW","OK"))) -> OK | P2: =K2-J2 -> -7359560 | Q2: =IF(J2=0,"n/a",P2/ABS(J2)) -> -0.026806639 | R2: =IF(ABS(P2)<Overview!$B$6,"OK",IF(J2=0,"REVIEW (zero base)",IF(ABS(P2/ABS(J2))>=Overview!$B$5,"REVIEW","OK"))) -> OK | S2: =IF(C2="EXPENSES",ABS(M2)+ROW()/1000000,0) -> 0
A3: 1 | B3: 101: City General | C3: REVENUES | D3: General (Non-Departmental) | E3: 101-000: Non Departmental-General Fund | F3: 41000: Total TAX REVENUES | G3: TANGIBLE TAX REVENUE | H3: -51020530 | I3: -53083749 | J3: -56635839 | K3: -58519773 | L3: -59679372 | M3: =J3-I3 -> -3552090 | N3: =IF(I3=0,"n/a",M3/ABS(I3)) -> -0.066914829 | O3: =IF(ABS(M3)<Overview!$B$6,"OK",IF(I3=0,"REVIEW (zero base)",IF(ABS(M3/ABS(I3))>=Overview!$B$5,"REVIEW","OK"))) -> OK | P3: =K3-J3 -> -1883934 | Q3: =IF(J3=0,"n/a",P3/ABS(J3)) -> -0.03326399 | R3: =IF(ABS(P3)<Overview!$B$6,"OK",IF(J3=0,"REVIEW (zero base)",IF(ABS(P3/ABS(J3))>=Overview!$B$5,"REVIEW","OK"))) -> OK | S3: =IF(C3="EXPENSES",ABS(M3)+ROW()/1000000,0) -> 0
A4: 2 | B4: 101: City General | C4: REVENUES | D4: General (Non-Departmental) | E4: 101-000: Non Departmental-General Fund | F4: 41000: Total TAX REVENUES | G4: EXCISE TAX REVENUE | H4: -22865816 | I4: -14961121 | J4: -13238754 | K4: -11407989 | L4: -8407989 | M4: =J4-I4 -> 1722367 | N4: =IF(I4=0,"n/a",M4/ABS(I4)) -> 0.11512286 | O4: =IF(ABS(M4)<Overview!$B$6,"OK",IF(I4=0,"REVIEW (zero base)",IF(ABS(M4/ABS(I4))>=Overview!$B$5,"REVIEW","OK"))) -> REVIEW | P4: =K4-J4 -> 1830765 | Q4: =IF(J4=0,"n/a",P4/ABS(J4)) -> 0.13828832 | R4: =IF(ABS(P4)<Overview!$B$6,"OK",IF(J4=0,"REVIEW (zero base)",IF(ABS(P4/ABS(J4))>=Overview!$B$5,"REVIEW","OK"))) -> REVIEW | S4: =IF(C4="EXPENSES",ABS(M4)+ROW()/1000000,0) -> 0
A5: 3 | B5: 101: City General | C5: REVENUES | D5: General (Non-Departmental) | E5: 101-000: Non Departmental-General Fund | F5: 42000: Total GRANTS | G5: PAYMENT IN LIEU OF TAXES | H5: -33187319 | I5: -14199131 | J5: -34077915 | K5: -34027865 | L5: -34027865 | M5: =J5-I5 -> -19878784 | N5: =IF(I5=0,"n/a",M5/ABS(I5)) -> -1.4 | O5: =IF(ABS(M5)<Overview!$B$6,"OK",IF(I5=0,"REVIEW (zero base)",IF(ABS(M5/ABS(I5))>=Overview!$B$5,"REVIEW","OK"))) -> REVIEW | P5: =K5-J5 -> 50050 | Q5: =IF(J5=0,"n/a",P5/ABS(J5)) -> 0.0014686931 | R5: =IF(ABS(P5)<Overview!$B$6,"OK",IF(J5=0,"REVIEW (zero base)",IF(ABS(P5/ABS(J5))>=Overview!$B$5,"REVIEW","OK"))) -> OK | S5: =IF(C5="EXPENSES",ABS(M5)+ROW()/1000000,0) -> 0
A6: 4 | B6: 101: City General | C6: REVENUES | D6: General (Non-Departmental) | E6: 101-000: Non Departmental-General Fund | F6: 42000: Total GRANTS | G6: SCHOOL DEBT CONSTRUCTION PAYMENTS | H6: -23511102 | I6: -25608576 | J6: -21703485 | K6: -23260714 | L6: -21308536 | M6: =J6-I6 -> 3905091 | N6: =IF(I6=0,"n/a",M6/ABS(I6)) -> 0.15249153 | O6: =IF(ABS(M6)<Overview!$B$6,"OK",IF(I6=0,"REVIEW (zero base)",IF(ABS(M6/ABS(I6))>=Overview!$B$5,"REVIEW","OK"))) -> REVIEW | P6: =K6-J6 -> -1557229 | Q6: =IF(J6=0,"n/a",P6/ABS(J6)) -> -0.071750182 | R6: =IF(ABS(P6)<Overview!$B$6,"OK",IF(J6=0,"REVIEW (zero base)",IF(ABS(P6/ABS(J6))>=Overview!$B$5,"REVIEW","OK"))) -> OK | S6: =IF(C6="EXPENSES",ABS(M6)+ROW()/1000000,0) -> 0
A7: 5 | B7: 101: City General | C7: REVENUES | D7: General (Non-Departmental) | E7: 101-000: Non Departmental-General Fund | F7: 42000: Total GRANTS | G7: TELEPHONE TAX | H7: -2262538 | I7: -2234814 | J7: -2262538 | K7: -2234814 | L7: -2234814 | M7: =J7-I7 -> -27724 | N7: =IF(I7=0,"n/a",M7/ABS(I7)) -> -0.012405507 | O7: =IF(ABS(M7)<Overview!$B$6,"OK",IF(I7=0,"REVIEW (zero base)",IF(ABS(M7/ABS(I7))>=Overview!$B$5,"REVIEW","OK"))) -> OK | P7: =K7-J7 -> 27724 | Q7: =IF(J7=0,"n/a",P7/ABS(J7)) -> 0.012253496 | R7: =IF(ABS(P7)<Overview!$B$6,"OK",IF(J7=0,"REVIEW (zero base)",IF(ABS(P7/ABS(J7))>=Overview!$B$5,"REVIEW","OK"))) -> OK | S7: =IF(C7="EXPENSES",ABS(M7)+ROW()/1000000,0) -> 0
A8: 6 | B8: 101: City General | C8: REVENUES | D8: General (Non-Departmental) | E8: 101-000: Non Departmental-General Fund | F8: 42000: Total GRANTS | G8: ADDITIONAL STATE OF RI AID | H8: 0 | I8: 0 | J8: 0 | K8: -750000 | L8: -1000000 | M8: =J8-I8 -> 0 | N8: =IF(I8=0,"n/a",M8/ABS(I8)) -> n/a | O8: =IF(ABS(M8)<Overview!$B$6,"OK",IF(I8=0,"REVIEW (zero base)",IF(ABS(M8/ABS(I8))>=Overview!$B$5,"REVIEW","OK"))) -> OK | P8: =K8-J8 -> -750000 | Q8: =IF(J8=0,"n/a",P8/ABS(J8)) -> n/a | R8: =IF(ABS(P8)<Overview!$B$6,"OK",IF(J8=0,"REVIEW (zero base)",IF(ABS(P8/ABS(J8))>=Overview!$B$5,"REVIEW","OK"))) -> REVIEW (zero base) | S8: =IF(C8="EXPENSES",ABS(M8)+ROW()/1000000,0) -> 0
A9: 7 | B9: 101: City General | C9: REVENUES | D9: General (Non-Departmental) | E9: 101-000: Non Departmental-General Fund | F9: 42000: Total GRANTS | G9: STATE REIMBURSEMENT EXCISE TAX | H9: -11661930 | I9: -20503369 | J9: -8543070 | K9: -24588929 | L9: -27588929 | M9: =J9-I9 -> 11960299 | N9: =IF(I9=0,"n/a",M9/ABS(I9)) -> 0.58333335 | O9: =IF(ABS(M9)<Overview!$B$6,"OK",IF(I9=0,"REVIEW (zero base)",IF(ABS(M9/ABS(I9))>=Overview!$B$5,"REVIEW","OK"))) -> REVIEW | P9: =K9-J9 -> -16045859 | Q9: =IF(J9=0,"n/a",P9/ABS(J9)) -> -1.878231 | R9: =IF(ABS(P9)<Overview!$B$6,"OK",IF(J9=0,"REVIEW (zero base)",IF(ABS(P9/ABS(J9))>=Overview!$B$5,"REVIEW","OK"))) -> REVIEW | S9: =IF(C9="EXPENSES",ABS(M9)+ROW()/1000000,0) -> 0
A10: 8 | B10: 101: City General | C10: REVENUES | D10: General (Non-Departmental) | E10: 101-000: Non Departmental-General Fund | F10: 42000: Total GRANTS | G10: DISTRESSED CITY REVENUE | H10: -5606831 | I10: -5155694 | J10: -1120549 | K10: -5265375 | L10: -5265375 | M10: =J10-I10 -> 4035145 | N10: =IF(I10=0,"n/a",M10/ABS(I10)) -> 0.78265797 | O10: =IF(ABS(M10)<Overview!$B$6,"OK",IF(I10=0,"REVIEW (zero base)",IF(ABS(M10/ABS(I10))>=Overview!$B$5,"REVIEW","OK"))) -> REVIEW | P10: =K10-J10 -> -4144826 | Q10: =IF(J10=0,"n/a",P10/ABS(J10)) -> -3.6989244 | R10: =IF(ABS(P10)<Overview!$B$6,"OK",IF(J10=0,"REVIEW (zero base)",IF(ABS(P10/ABS(J10))>=Overview!$B$5,"REVIEW","OK"))) -> REVIEW | S10: =IF(C10="EXPENSES",ABS(M10)+ROW()/1000000,0) -> 0
A11: 9 | B11: 101: City General | C11: REVENUES | D11: General (Non-Departmental) | E11: 101-000: Non Departmental-General Fund | F11: 42000: Total GRANTS | G11: MEALS & BEVERAGES TAX | H11: -5586483 | I11: -5252178 | J11: -4972708 | K11: -5282907 | L11: -6650532 | M11: =J11-I11 -> 279470 | N11: =IF(I11=0,"n/a",M11/ABS(I11)) -> 0.053210306 | O11: =IF(ABS(M11)<Overview!$B$6,"OK",IF(I11=0,"REVIEW (zero base)",IF(ABS(M11/ABS(I11))>=Overview!$B$5,"REVIEW","OK"))) -> OK | P11: =K11-J11 -> -310199 | Q11: =IF(J11=0,"n/a",P11/ABS(J11)) -> -0.062380297 | R11: =IF(ABS(P11)<Overview!$B$6,"OK",IF(J11=0,"REVIEW (zero base)",IF(ABS(P11/ABS(J11))>=Overview!$B$5,"REVIEW","OK"))) -> OK | S11: =IF(C11="EXPENSES",ABS(M11)+ROW()/1000000,0) -> 0
A12: 10 | B12: 101: City General | C12: REVENUES | D12: General (Non-Departmental) | E12: 101-000: Non Departmental-General Fund | F12: 42100: Total FEDERAL GRANTS | G12: CORONAVIRUS RELIEF FUNDS | H12: 0 | I12: 0 | J12: -26494542 | K12: 0 | L12: 0 | M12: =J12-I12 -> -26494542 | N12: =IF(I12=0,"n/a",M12/ABS(I12)) -> n/a | O12: =IF(ABS(M12)<Overview!$B$6,"OK",IF(I12=0,"REVIEW (zero base)",IF(ABS(M12/ABS(I12))>=Overview!$B$5,"REVIEW","OK"))) -> REVIEW (zero base) | P12: =K12-J12 -> 26494542 | Q12: =IF(J12=0,"n/a",P12/ABS(J12)) -> 1 | R12: =IF(ABS(P12)<Overview!$B$6,"OK",IF(J12=0,"REVIEW (zero base)",IF(ABS(P12/ABS(J12))>=Overview!$B$5,"REVIEW","OK"))) -> REVIEW | S12: =IF(C12="EXPENSES",ABS(M12)+ROW()/1000000,0) -> 0
A13: 11 | B13: 101: City General | C13: REVENUES | D13: General (Non-Departmental) | E13: 101-000: Non Departmental-General Fund | F13: 42200: Total STATE GRANTS | G13: STATE GRANT | H13: 0 | I13: -155408 | J13: 0 | K13: 0 | L13: 0 | M13: =J13-I13 -> 155408 | N13: =IF(I13=0,"n/a",M13/ABS(I13)) -> 1 | O13: =IF(ABS(M13)<Overview!$B$6,"OK",IF(I13=0,"REVIEW (zero base)",IF(ABS(M13/ABS(I13))>=Overview!$B$5,"REVIEW","OK"))) -> OK | P13: =K13-J13 -> 0 | Q13: =IF(J13=0,"n/a",P13/ABS(J13)) -> n/a | R13: =IF(ABS(P13)<Overview!$B$6,"OK",IF(J13=0,"REVIEW (zero base)",IF(ABS(P13/ABS(J13))>=Overview!$B$5,"REVIEW","OK"))) -> OK | S13: =IF(C13="EXPENSES",ABS(M13)+ROW()/1000000,0) -> 0
... A1534: 1532 | B1534: 101: City General | C1534: EXPENSES | D1534: Mayoral Offices | E1534: 101-104: City Sergeant | F1534: 52100: Total G&A SERVICES | G1534: POSTAGE | H1534: 0 | I1534: 0 | J1534: 0 | K1534: 0 | L1534: 0 | M1534: =J1534-I1534 -> 0 | N1534: =IF(I1534=0,"n/a",M1534/ABS(I1534)) -> n/a | O1534: =IF(ABS(M1534)<Overview!$B$6,"OK",IF(I1534=0,"REVIEW (zero base)",IF(ABS(M1534/ABS(I1534))>=Overview!$B$5,"REVIEW","OK"))) -> OK | P1534: =K1534-J1534 -> 0 | Q1534: =IF(J1534=0,"n/a",P1534/ABS(J1534)) -> n/a | R1534: =IF(ABS(P1534)<Overview!$B$6,"OK",IF(J1534=0,"REVIEW (zero base)",IF(ABS(P1534/ABS(J1534))>=Overview!$B$5,"REVIEW","OK"))) -> OK | S1534: =IF(C1534="EXPENSES",ABS(M1534)+ROW()/1000000,0) -> 0.001534
